vulcano/__init__.py
vulcano/app/__init__.py
vulcano/app/classes.py
vulcano/app/test_classes.py
vulcano/command/__init__.py
vulcano/command/builtin.py
vulcano/command/classes.py
vulcano/command/models.py
vulcano/command/parser.py
vulcano/command/test_classes.py
vulcano/command/test_parser.py
vulcano/core/__init__.py
vulcano/core/classes.py
vulcano/core/test_classes.py
vulcano-0.0.3.dist-info/METADATA
vulcano-0.0.3.dist-info/WHEEL
vulcano-0.0.3.dist-info/top_level.txt
vulcano-0.0.3.dist-info/RECORD
