Metadata-Version: 2.1
Name: vulcano
Version: 0.0.3
Summary: Vulcano
Home-page: https://github.com/dgarana/vulcano
Author: David Garaña
License: UNKNOWN
Keywords: console development cli repl
Platform: UNKNOWN
Classifier: Development Status :: 3 - Alpha
Classifier: Intended Audience :: Developers
Classifier: Topic :: Software Development :: Build Tools
Classifier: License :: OSI Approved :: MIT License
Classifier: Programming Language :: Python :: 2
Classifier: Programming Language :: Python :: 2.7
Classifier: Programming Language :: Python :: 3
Classifier: Programming Language :: Python :: 3.4
Classifier: Programming Language :: Python :: 3.5
Classifier: Programming Language :: Python :: 3.6
Classifier: Programming Language :: Python :: 3.7
Requires-Dist: pyparsing
Requires-Dist: prompt-toolkit
